img2jb2pdf/__init__.py
img2jb2pdf-2023.7.22.0.dist-info/LICENSE
img2jb2pdf-2023.7.22.0.dist-info/METADATA
img2jb2pdf-2023.7.22.0.dist-info/WHEEL
img2jb2pdf-2023.7.22.0.dist-info/top_level.txt
img2jb2pdf-2023.7.22.0.dist-info/RECORD
