Metadata-Version: 2.1
Name: img2jb2pdf
Version: 2023.7.22.0
Summary: 将二值图像转换为 JBIG2Decode 编码的 PDF
Home-page: https://github.com/DracoUnion/img2jb2pdf
Author: wizardforcel
Author-email: wizard.z@qq.com
Keywords: pdf,image,binarize,jbig2
Classifier: Development Status :: 4 - Beta
Classifier: Environment :: Console
Classifier: Intended Audience :: Developers
Classifier: License :: Other/Proprietary License
Classifier: Natural Language :: Chinese (Simplified)
Classifier: Natural Language :: English
Classifier: Operating System :: Microsoft :: Windows
Classifier: Operating System :: POSIX :: Linux
Classifier: Programming Language :: Python :: 3
Classifier: Programming Language :: Python :: 3 :: Only
Classifier: Programming Language :: Python :: 3.6
Classifier: Programming Language :: Python :: 3.7
Classifier: Topic :: Software Development :: Documentation
Classifier: Topic :: Scientific/Engineering :: Image Processing
Classifier: Topic :: Utilities
Requires-Python: >=3.6
License-File: LICENSE
